coinbase_agentkit_autogen/__init__.py
coinbase_agentkit_autogen/autogen_tools.py
coinbase_agentkit_autogen-0.1.0.dist-info/METADATA
coinbase_agentkit_autogen-0.1.0.dist-info/WHEEL
coinbase_agentkit_autogen-0.1.0.dist-info/RECORD
