Metadata-Version: 2.4
Name: coinbase-agentkit-autogen
Version: 0.1.0
Summary: Coinbase AgentKit Autogen extension
Author-email: Taejin Kim <kitto727@gmail.com>
License-Expression: Apache-2.0
Keywords: agent,ai,autogen,cdp,coinbase,crypto,sdk
Requires-Python: ~=3.10
Requires-Dist: autogen-agentchat<0.8,>=0.7.1
Requires-Dist: autogen-ext[openai]<0.8,>=0.7.1
Requires-Dist: coinbase-agentkit<0.8,>=0.7.2
Requires-Dist: nest-asyncio<2,>=1.6.0
Requires-Dist: pytest-asyncio<0.26,>=0.25.3
Requires-Dist: python-dotenv<2,>=1.0.1
